docker/__init__.py
docker/aws_ecr.py
docker/helper.py
docker/quay_io.py
scing/__init__.py
scing/build.py
scing/config.py
scing/core.py
scing/delete.py
scing/download.py
scing/error.py
scing/install.py
scing/push.py
scing/ten_x_eula.py
scing/utils.py
scing/version.py
scing-0.8.2.data/scripts/scing
scing-0.8.2.dist-info/LICENSE
scing-0.8.2.dist-info/METADATA
scing-0.8.2.dist-info/WHEEL
scing-0.8.2.dist-info/top_level.txt
scing-0.8.2.dist-info/RECORD
