Metadata-Version: 2.1
Name: scing
Version: 0.8.2
Summary: Single-Cell pIpeliNe Garden
Home-page: https://github.com/hisplan/scing
Author: Jaeyoung Chun
Author-email: chunj@mskcc.org
Classifier: Programming Language :: Python :: 3
Classifier: License :: OSI Approved :: MIT License
Classifier: Operating System :: OS Independent
Requires-Python: >=3.7
License-File: LICENSE
Requires-Dist: pyyaml (>=5.4.1)
Requires-Dist: requests (>=2.24.0)
Requires-Dist: tqdm (>=4.62.0)
Requires-Dist: cromwell-tools (>=2.4.1)
Requires-Dist: beautifulsoup4 (>=4.9.3)
Requires-Dist: requests-html (>=0.10.0)
Provides-Extra: dev
Requires-Dist: pytest ; extra == 'dev'
Requires-Dist: black (>=21.7b0) ; extra == 'dev'
